tipe_sim/__init__.py
tipe_sim/simulator.py
tipe_sim-1.2.1.dist-info/METADATA
tipe_sim-1.2.1.dist-info/WHEEL
tipe_sim-1.2.1.dist-info/top_level.txt
tipe_sim-1.2.1.dist-info/RECORD
