Metadata-Version: 2.4
Name: tipe_sim
Version: 1.2.1
Summary: A Python library to generate professional TIPE simulations using the Gemini API.
Home-page: https://github.com/yourusername/tipe_sim
Author: Aadidil ilyas
Author-email: 
Classifier: Programming Language :: Python :: 3
Classifier: License :: OSI Approved :: MIT License
Classifier: Operating System :: OS Independent
Requires-Python: >=3.6
Requires-Dist: requests
Dynamic: author
Dynamic: classifier
Dynamic: description
Dynamic: description-content-type
Dynamic: home-page
Dynamic: requires-dist
Dynamic: requires-python
Dynamic: summary
